{
  "login_and_view_portals": {
    "110": {
      "r": [],
      "c": [
        "browser-metrics-plugin.contrib"
      ],
      "xc": [
        "jira.webresources:almond",
        "customerportal",
        "com.atlassian.analytics.analytics-client:js-events",
        "async-chunk-cv-help-center-portal-page"
      ],
      "xr": []
    },
    "115": {
      "models": [
        "popularPortals",
        "recentRequestTypes"
      ],
      "options": {}
    },
    "120": [{"name":"servicedesk.page.view.customerview.login","properties":{"sdVersion":"4.13.0"},"timeDelta":-1792},{"name":"servicedesk.page.view.customerview.session","properties":{"count":1,"path":"cv.login","sdVersion":"4.13.0"},"timeDelta":-741},{"name":"servicedesk.smartportal.title.announcement.view.none","properties":{"sdVersion":"4.13.0"},"timeDelta":-175},{"name":"servicedesk.customerview.smartportal.viewed","properties":{"sdVersion":"4.13.0"},"timeDelta":-132},{"name":"browser.metrics.navigation","properties":{"apdex":"0.5","firstPaint":"647","isInitial":"true","journeyId":"9ed6aa46-413a-43fb-820a-75dfcc2ed337","key":"servicedesk.cv.shared.portal","navigationType":"0","readyForUser":"1655","redirectCount":"0","resourceLoadedEnd":"289","resourceLoadedStart":245.64000000827946,"threshold":"1000","unloadEventStart":"202","unloadEventEnd":"203","fetchStart":"23","domainLookupStart":"23","domainLookupEnd":"23","connectStart":"23","connectEnd":"23","requestStart":"44","responseStart":"187","responseEnd":"313","domLoading":"206","domInteractive":"588","domContentLoadedEventStart":"588","domContentLoadedEventEnd":"595","domComplete":"1310","loadEventStart":"1310","loadEventEnd":"1316","userAgent":"Mozilla/5.0 (X11; Linux x86_64) AppleWebKit/537.36 (KHTML, like Gecko) Chrome/87.0.4280.66 Safari/537.36","effectiveType":"4g","downlink":1.5,"rtt":100,"applicationHash":"8c68d8036d917652ef7564456d59d80184b5a77e","resourceTiming":"{\"☠\":[\"2,6t,6t,,,6t,,6t,6t,6t\",\"2,6u,81,7s,7r,6u,,6u,6u,6u\",\"3,fm,i4,g3,g1,fm,,fm,fm,fm\",\"3,fn,hk,gp,gn,fn,,fn,fn,fn\",\"4,gr,gr,,,gr,,gr,gr,gr\",\"5,nt,s3,rx,o9,nt,,nt,nt,nt\",\"3,zg,zw,zq,zo,zg,,zg,zg,zg\",\"5,10c,158,155,11j,10c,,10c,10c,10c\"]}","mark.@grammarly-extension:checkScriptInitStart":"[1114]","mark.@grammarly-extension:checkScriptInitEnd":"[1122]","userTimingRaw":"{\"marks\":{\"@grammarly-extension:checkScriptInitStart\":[1114],\"@grammarly-extension:checkScriptInitEnd\":[1122]},\"measures\":{}}","experiments":"[]","connectionEffectiveType":"4g","connectionDownlink":1.5,"connectionRTT":100},"timeDelta":-101}]
  },
  "view_portal": {
    "205": {"r":[],"c":["browser-metrics-plugin.contrib"],"xc":["jira.webresources:almond","customerportal","com.atlassian.analytics.analytics-client:js-events","async-chunk-cv-landing-page"],"xr":[]},
    "210": [{"name":"servicedesk.page.view.customerview.session","properties":{"count":1,"path":"cv.shared.portal","sdVersion":"4.13.0"},"timeDelta":-621},{"name":"servicedesk.page.view.portal.global.title.announcement.view.none","properties":{"sdVersion":"4.13.0"},"timeDelta":-84},{"name":"servicedesk.page.view.customerview","properties":{"sdVersion":"4.13.0","projectId":10147},"timeDelta":-48},{"name":"browser.metrics.navigation","properties":{"apdex":"0.5","firstPaint":"876","isInitial":"true","journeyId":"9ed6aa46-413a-43fb-820a-75dfcc2ed337","key":"servicedesk.cv.portal.landing","navigationType":"0","readyForUser":"1802","redirectCount":"0","resourceLoadedEnd":"634","resourceLoadedStart":441.19499999214895,"threshold":"1000","unloadEventStart":"395","unloadEventEnd":"396","fetchStart":"8","domainLookupStart":"57","domainLookupEnd":"57","connectStart":"57","connectEnd":"243","requestStart":"243","responseStart":"378","responseEnd":"437","domLoading":"401","domInteractive":"903","domContentLoadedEventStart":"903","domContentLoadedEventEnd":"914","domComplete":"1513","loadEventStart":"1513","loadEventEnd":"1517","userAgent":"Mozilla/5.0 (X11; Linux x86_64) AppleWebKit/537.36 (KHTML, like Gecko) Chrome/87.0.4280.66 Safari/537.36","effectiveType":"4g","downlink":1.5,"rtt":100,"applicationHash":"8c68d8036d917652ef7564456d59d80184b5a77e","resourceTiming":"{\"☠\":[\"2,c9,c9,,,c9,,c9,c9,c9\",\"2,c9,hm,gt,d8,c9,,c9,c9,c9\",\"3,m9,p3,n5,n4,m9,,m9,m9,m9\",\"3,ma,yg,r9,nl,ma,,ma,ma,ma\",\"4,n9,n9,,,n9,,n9,n9,n9\",\"5,v1,yv,yp,v4,v1,,v1,v1,v1\",\"3,113,155,14x,11c,113,,113,113,113\",\"5,160,1al,1ai,16x,160,,160,160,160\"]}","mark.@grammarly-extension:checkScriptInitStart":"[1311]","mark.@grammarly-extension:checkScriptInitEnd":"[1326]","userTimingRaw":"{\"marks\":{\"@grammarly-extension:checkScriptInitStart\":[1311],\"@grammarly-extension:checkScriptInitEnd\":[1326]},\"measures\":{}}","experiments":"[]","connectionEffectiveType":"4g","connectionDownlink":1.5,"connectionRTT":100},"timeDelta":-29}]
  },
  "view_requests": {
    "250": {"r":[],"c":["com.atlassian.servicedesk.frontend-webpack-plugin:17"],"xc":["jira.webresources:almond","customerportal","com.atlassian.analytics.analytics-client:js-events","async-chunk-cv-landing-page","browser-metrics-plugin.contrib"],"xr":[]},
    "260": [{"name":"servicedesk.page.view.requests.global.title.announcement.view.none","properties":{"sdVersion":"4.13.0","projectId":10001},"timeDelta":-688},{"name":"servicedesk.page.view.customerview.allrequests","properties":{"sdVersion":"4.13.0","projectId":10001},"timeDelta":-672},{"name":"browser.metrics.navigation","properties":{"apdex":"0","firstPaint":"265","isInitial":"true","journeyId":"ba5f75b5-0e2e-4e06-bc45-ddd1c9a03cc2","key":"servicedesk.cv.all.requests","navigationType":"0","readyForUser":"52132","redirectCount":"0","resourceLoadedEnd":"262","resourceLoadedStart":200.1600000075996,"threshold":"1000","fetchStart":"11","domainLookupStart":"11","domainLookupEnd":"11","connectStart":"11","connectEnd":"11","requestStart":"18","responseStart":"180","responseEnd":"231","domLoading":"189","domInteractive":"265","domContentLoadedEventStart":"265","domContentLoadedEventEnd":"265","domComplete":"480","loadEventStart":"480","loadEventEnd":"482","userAgent":"Mozilla/5.0 (Windows NT 10.0; Win64; x64) AppleWebKit/537.36 (KHTML, like Gecko) Chrome/86.0.4240.111 Safari/537.36","effectiveType":"4g","downlink":2.25,"rtt":100,"applicationHash":"8c68d8036d917652ef7564456d59d80184b5a77e","resourceTiming":"{\"â \":[\"2,5k,5s,5n,5m,5k,,5k,5k,5k\",\"2,5k,5r,5n,5m,5k,,5k,5k,5k\",\"3,6y,7g,71,70,6y,,6y,6y,6y\",\"3,6y,7a,74,71,6y,,6y,6y,6y\",\"4,7c,7c,,,7c,,7c,7c,7c\",\"5,89,cd,cc,8a,89,,89,89,89\",\"3,d7,d9,d8,d8,d7,,d7,d7,d7\",\"5,dd,hg,hg,de,dd,,dd,dd,dd\",\"5,o1,s5,s5,o6,o1,,o1,o1,o1\",\"5,13f8,13jo,13jm,13fk,13f8,,13f8,13f8,13f8\",\"2,13js,13nx,13nw,13jw,13js,,13js,13js,13js\",\"3,13jt,13xq,13pw,13jy,13jt,,13jt,13jt,13jt\",\"5,13y0,1479,1478,13y2,13y0,,13y0,13y0,13y0\"]}","mark.@grammarly-extension:checkScriptInitStart":"[402]","mark.@grammarly-extension:checkScriptInitEnd":"[409]","mark.@grammarly-extension:callExecuteContentScript":"[41420]","mark.@grammarly-extension:initStart":"[41718]","mark.@grammarly-extension:initEnd":"[41735]","userTimingRaw":"{\"marks\":{\"@grammarly-extension:checkScriptInitStart\":[402],\"@grammarly-extension:checkScriptInitEnd\":[409],\"@grammarly-extension:callExecuteContentScript\":[41420],\"@grammarly-extension:initStart\":[41718],\"@grammarly-extension:initEnd\":[41735]},\"measures\":{}}","experiments":"[]","connectionEffectiveType":"4g","connectionDownlink":2.25,"connectionRTT":100},"timeDelta":-655}],
    "300": {"r":[],"c":["com.atlassian.servicedesk.frontend-webpack-plugin:17"],"xc":["jira.webresources:almond","customerportal","com.atlassian.analytics.analytics-client:js-events","async-chunk-cv-landing-page","browser-metrics-plugin.contrib"],"xr":[]},
    "325": [{"name":"servicedesk.customerview.requests.search.filter.changed","properties":{"sdVersion":"4.13.0"},"timeDelta":-2987},{"name":"servicedesk.page.view.requests.global.title.announcement.view.none","properties":{"sdVersion":"4.13.0"},"timeDelta":-2781},{"name":"servicedesk.page.view.customerview.allrequests","properties":{"sdVersion":"4.13.0"},"timeDelta":-2768},{"name":"browser.metrics.navigation","properties":{"apdex":"1","isInitial":"false","journeyId":"eff25cfb-167f-44d9-95b6-07adc3ac84cf","key":"servicedesk.cv.all.requests","readyForUser":"221","threshold":"1000","userAgent":"Mozilla/5.0 (Windows NT 10.0; Win64; x64) AppleWebKit/537.36 (KHTML, like Gecko) Chrome/86.0.4240.111 Safari/537.36","effectiveType":"4g","downlink":7.7,"rtt":100,"applicationHash":"8c68d8036d917652ef7564456d59d80184b5a77e","resourceTiming":"{\"â \":[\"5,3,55,54,g,3,,3,3,3\"]}","userTimingRaw":"{\"marks\":{},\"measures\":{}}","experiments":"[]","connectionEffectiveType":"4g","connectionDownlink":7.7,"connectionRTT":100},"timeDelta":-2747}]
  },
  "view_request": {
    "355": [{"name":"servicedesk.customerview.issue.opened","properties":{"isIncident":false,"issueId":10200,"archived":false,"sdVersion":"4.13.0","projectId":10015},"timeDelta":-1821},{"name":"servicedesk.page.view.customerview.requestDetails","properties":{"sdVersion":"4.13.0","projectId":10015},"timeDelta":-1811},{"name":"browser.metrics.navigation","properties":{"apdex":"1","isInitial":"false","journeyId":"eff25cfb-167f-44d9-95b6-07adc3ac84cf","key":"servicedesk.cv.request.details","readyForUser":"220","threshold":"1000","userAgent":"Mozilla/5.0 (Windows NT 10.0; Win64; x64) AppleWebKit/537.36 (KHTML, like Gecko) Chrome/86.0.4240.111 Safari/537.36","effectiveType":"4g","downlink":10,"rtt":50,"applicationHash":"8c68d8036d917652ef7564456d59d80184b5a77e","resourceTiming":"{\"â \":[\"5,d,59,58,h,d,,d,d,d\"]}","userTimingRaw":"{\"marks\":{},\"measures\":{}}","experiments":"[]","connectionEffectiveType":"4g","connectionDownlink":10,"connectionRTT":50},"timeDelta":-1802}]
  },
  "add_comment": {
    "365": [{"name":"servicedesk.page.view.customerview.comment","properties":{"sdVersion":"4.13.0","projectId":10011},"timeDelta":-203}]
  },
  "share_request": {
    "410": [{"name":"servicedesk.page.view.customerview.participants.add.opened","properties":{"sdVersion":"4.13.0","projectId":10008},"timeDelta":-4937}],
    "460": {"models":["user","organisations","sharedPortal","helpCenterBranding","portal","reqDetails","portalWebFragments"],"options":{"portalId":"${request_portal_id}","portal":{"id":"${request_portal_id}"},"reqDetails":{"key":"${request_key}"},"portalWebFragments":{"portalPage":"VIEW_REQUEST"}}}
  },
  "share_request_org": {
    "510": [{"name":"servicedesk.page.view.customerview.participants.add.opened","properties":{"sdVersion":"4.13.0","projectId":10008},"timeDelta":-4937}]
  },
  "create_request": {
    "602": [{"name":"servicedesk.customerview.smartportal.browse.popular.portals.portal.clicked","properties":{"index":0,"sdVersion":"4.13.0"},"timeDelta":-1193},{"name":"servicedesk.page.view.portal.global.title.announcement.view.none","properties":{"sdVersion":"4.13.0"},"timeDelta":-930},{"name":"servicedesk.page.view.customerview","properties":{"sdVersion":"4.13.0","projectId":10188},"timeDelta":-922},{"name":"browser.metrics.navigation","properties":{"apdex":"0","firstPaint":"297","isInitial":"true","journeyId":"1288b6b6-dc3c-495f-b444-f68ec3b32cb3","key":"servicedesk.cv.portal.landing","navigationType":"0","readyForUser":"5549014","redirectCount":"0","resourceLoadedEnd":"275","resourceLoadedStart":223.40000001713634,"threshold":"1000","unloadEventStart":"207","unloadEventEnd":"207","fetchStart":"2","domainLookupStart":"2","domainLookupEnd":"2","connectStart":"2","connectEnd":"2","requestStart":"5","responseStart":"198","responseEnd":"269","domLoading":"208","domInteractive":"276","domContentLoadedEventStart":"276","domContentLoadedEventEnd":"277","domComplete":"737","loadEventStart":"737","loadEventEnd":"739","userAgent":"Mozilla/5.0 (Windows NT 10.0; Win64; x64) AppleWebKit/537.36 (KHTML, like Gecko) Chrome/86.0.4240.198 Safari/537.36","effectiveType":"4g","downlink":10,"rtt":50,"applicationHash":"8c68d8036d917652ef7564456d59d80184b5a77e","resourceTiming":"{\"â \":[\"2,67,67,,,67,,67,67,67\",\"2,67,b0,ax,6r,67,,67,67,67\",\"3,75,7n,76,76,75,,75,75,75\",\"3,75,di,cz,7p,75,,75,75,75\",\"4,7r,7r,,,7r,,7r,7r,7r\",\"5,8w,e6,e5,8x,8w,,8w,8w,8w\",\"3,ev,k6,k4,ex,ev,,ev,ev,ev\",\"5,ke,pq,pp,ki,ke,,ke,ke,ke\",\"5,ow,u7,u7,oy,ow,,ow,ow,ow\",\"5,2k3,2pa,2p9,2k9,2k3,,2k3,2k3,2k3\",\"2,2pd,2ug,2ue,2pe,2pd,,2pd,2pd,2pd\",\"3,2pd,393,2uf,2pf,2pd,,2pd,2pd,2pd\",\"5,3a1,3hj,3hi,3a3,3a1,,3a1,3a1,3a1\",\"4,3hw,3hw,,,3hw,,3hw,3hw,3hw\",\"5,4p7,4uh,4uh,4p8,4p7,,4p7,4p7,4p7\",\"5,zbw,zzm,zzm,zc2,zbw,,zbw,zbw,zbw\",\"5,zzt,105d,105c,100a,zzt,,zzt,zzt,zzt\",\"5,zzu,10e4,10b1,105n,105m,,105m,105m,105m,105k,zzu\",\"2,105g,10an,10al,105i,105g,,105g,105g,105g\",\"3,105h,10e0,109v,105j,105h,,105h,105h,105h\",\"5,10ee,10mk,10mj,10eh,10ee,,10ee,10ee,10ee\",\"4,10nf,10nf,,,10nf,,10nf,10nf,10nf\",\"4,10nh,10sn,10sl,10nj,10nh,,10nh,10nh,10nh\",\"5,13m7,13rb,13ra,13ma,13m7,,13m7,13m7,13m7\",\"5,25qf3,25r6m,25r6l,25qf8,25qf3,,25qf3,25qf3,25qf3\",\"4,25r6y,25r6y,,,25r6y,,25r6y,25r6y,25r6y\",\"5,25tpb,25ug7,25ug6,25tpj,25tpb,,25tpb,25tpb,25tpb\",\"4,25ugi,25ugi,,,25ugi,,25ugi,25ugi,25ugi\",\"5,25v1h,25v5n,25v5m,25v1j,25v1h,,25v1h,25v1h,25v1h\",\"4,25vby,25vby,,,25vby,,25vby,25vby,25vby\",\"5,260by,260zn,260zl,260c0,260by,,260by,260by,260by\",\"5,260zy,2622p,2619f,2614m,2614m,,2614m,2614m,2614m,2614k,260zy\",\"5,2610g,2618i,2618g,2610i,2610g,,2610g,2610g,2610g\",\"4,2619k,2619k,,,2619k,,2619k,2619k,2619k\",\"4,2619m,2619o,2619n,2619n,2619m,,2619m,2619m,2619m\",\"5,262vu,2630x,2630x,262vw,262vu,,262vu,262vu,262vu\",\"4,26t4u,26t4u,,,26t4u,,26t4u,26t4u,26t4u\",\"5,2xuud,2xv69,2xv68,2xuzn,2xuzn,,2xuuk,2xuuk,2xuuk\",\"-1,2xuul,2xv3s,2xv3q,2xuzq,2xuzq,,2xuuo,2xuuo,2xuuo\",\"4,2xv6p,2xv6p,,,2xv6p,,2xv6p,2xv6p,2xv6p\",\"5,2xx2e,2xx6j,2xx6j,2xx2f,2xx2e,,2xx2e,2xx2e,2xx2e\",\"5,2yw6f,2ywgd,2ywgc,2yw92,2yw6f,,2yw6f,2yw6f,2yw6f\",\"4,2ywgp,2ywgp,,,2ywgp,,2ywgp,2ywgp,2ywgp\",\"5,2yzsl,2yzxl,2yzxl,2yzsm,2yzsl,,2yzsl,2yzsl,2yzsl\",\"5,2z5gk,2z5uh,2z5ug,2z5gn,2z5gk,,2z5gk,2z5gk,2z5gk\",\"5,2z5up,2z6b5,2z662,2z60i,2z60h,,2z60h,2z60h,2z60h,2z60f,2z5up\",\"5,2z5uu,2z639,2z638,2z5vg,2z5uu,,2z5uu,2z5uu,2z5uu\",\"4,2z640,2z640,,,2z640,,2z640,2z640,2z640\",\"4,2z642,2z687,2z685,2z644,2z642,,2z642,2z642,2z642\",\"5,2z7o0,2z7sa,2z7s9,2z7o1,2z7o0,,2z7o0,2z7o0,2z7o0\",\"5,38l0q,38lbu,38lbt,38l5p,38l5p,,38l0u,38l0u,38l0u\",\"4,38lc5,38lc5,,,38lc5,,38lc5,38lc5,38lc5\",\"5,38m3t,38m7z,38m7y,38m3u,38m3t,,38m3t,38m3t,38m3t\",\"5,38pd7,38pht,38phr,38pde,38pd7,,38pd7,38pd7,38pd7\",\"2,38phw,38pm6,38pm4,38phy,38phw,,38phw,38phw,38phw\",\"3,38phx,38q9u,38ppl,38phy,38phx,,38phx,38phx,38phx\",\"5,38qa2,38qgx,38qgw,38qa4,38qa2,,38qa2,38qa2,38qa2\",\"4,38qhc,38qhc,,,38qhc,,38qhc,38qhc,38qhc\",\"5,38qhl,38qx8,38qx7,38qhn,38qhl,,38qhl,38qhl,38qhl\",\"5,38s0z,38s7i,38s7h,38s14,38s0z,,38s0z,38s0z,38s0z\",\"4,38s80,38s80,,,38s80,,38s80,38s80,38s80\",\"5,38tvc,38u26,38u25,38tvp,38tvc,,38tvc,38tvc,38tvc\",\"5,38txz,38u24,38u24,38ty0,38txz,,38txz,38txz,38txz\",\"4,38u2i,38u2i,,,38u2i,,38u2i,38u2i,38u2i\",\"5,38xrd,38xxu,38xxt,38xrq,38xrd,,38xrd,38xrd,38xrd\",\"5,38xx6,38y1c,38y1b,38xx7,38xx6,,38xx6,38xx6,38xx6\",\"4,38xy8,38xy8,,,38xy8,,38xy8,38xy8,38xy8\",\"5,38yxg,38z49,38z48,38yxk,38yxg,,38yxg,38yxg,38yxg\",\"5,38z52,38zjn,38zjm,38z54,38z52,,38z52,38z52,38z52\",\"4,38z54,38z54,,,38z54,,38z54,38z54,38z54\",\"5,391wg,3920m,3920m,391wi,391wg,,391wg,391wg,391wg\",\"5,39fu5,39g0i,39g0h,39fuf,39fu5,,39fu5,39fu5,39fu5\",\"4,39g12,39g12,,,39g12,,39g12,39g12,39g12\",\"5,39hh7,39hld,39hld,39hha,39hh7,,39hh7,39hh7,39hh7\",\"5,39k5e,39kc4,39kc3,39k5q,39k5e,,39k5e,39k5e,39k5e\",\"4,39kcl,39kcl,,,39kcl,,39kcl,39kcl,39kcl\",\"5,39lge,39lkl,39lkk,39lgh,39lge,,39lge,39lge,39lge\",\"5,39rpb,39s1s,39s1r,39rpe,39rpb,,39rpb,39rpb,39rpb\",\"5,39s20,39sdn,39sav,39s6f,39s6e,,39s6e,39s6e,39s6e,39s6c,39s20\",\"5,39s27,39sac,39sab,39s2i,39s27,,39s27,39s27,39s27\",\"4,39sb5,39sb5,,,39sb5,,39sb5,39sb5,39sb5\",\"4,39sb7,39sfd,39sfc,39sb9,39sb7,,39sb7,39sb7,39sb7\",\"5,39tai,39tep,39teo,39taj,39tai,,39tai,39tai,39tai\",\"5,3ans0,3anz7,3anz5,3ans9,3ans0,,3ans0,3ans0,3ans0\",\"4,3anzr,3anzr,,,3anzr,,3anzr,3anzr,3anzr\",\"5,3ao01,3aoep,3aoeo,3ao02,3ao01,,3ao01,3ao01,3ao01\",\"5,3aqi8,3aqmz,3aqmy,3aqia,3aqi8,,3aqi8,3aqi8,3aqi8\",\"5,3axfz,3axmn,3axmm,3axgh,3axfz,,3axfz,3axfz,3axfz\"]}","mark.@grammarly-extension:checkScriptInitStart":"[501]","mark.@grammarly-extension:checkScriptInitEnd":"[504]","mark.@grammarly-extension:callExecuteContentScript":"[6613]","mark.@grammarly-extension:initStart":"[6908]","mark.@grammarly-extension:initEnd":"[6930]","mark.@grammarly-extension:gButtonShow":"[7224,3637084,4992992,5455880,5490557]","userTimingRaw":"{\"marks\":{\"@grammarly-extension:checkScriptInitStart\":[501],\"@grammarly-extension:checkScriptInitEnd\":[504],\"@grammarly-extension:callExecuteContentScript\":[6613],\"@grammarly-extension:initStart\":[6908],\"@grammarly-extension:initEnd\":[6930],\"@grammarly-extension:gButtonShow\":[7224,3637084,4992992,5455880,5490557]},\"measures\":{}}","experiments":"[]","connectionEffectiveType":"4g","connectionDownlink":10,"connectionRTT":50},"timeDelta":-913}]
  }
}